{
  "2025-4-24": {
    "bazzite-deck": 5350000,
    "bazzite": 2850000,
    "silverblue-main": 1590000,
    "akmods": 1540000,
    "bazzite-nvidia": 1510000,
    "silverblue-nvidia": 1110000,
    "bluefin-dx": 1050000,
    "bazzite-nvidia-open": 917000,
    "kinoite-main": 863000,
    "kinoite-nvidia": 849000,
    "bazzite-gnome": 835000,
    "bazzite-deck-gnome": 820000,
    "akmods-nvidia": 782000,
    "bluefin": 725000,
    "base-nvidia": 548000,
    "vauxite-nvidia": 547000,
    "bluefin-dx-nvidia": 528000,
    "aurora-dx": 505000,
    "bazzite-gnome-nvidia": 493000,
    "ucore": 467000,
    "base-main": 408000,
    "mate-nvidia": 392000,
    "lxqt-nvidia": 392000,
    "main-kernel": 303000,
    "bazzite-gnome-nvidia-open": 287000,
    "sericea-nvidia": 268000,
    "ucore-hci": 266000,
    "aurora": 259000,
    "bluefin-nvidia": 250000,
    "vauxite-main": 241000,
    "bazzite-ally": 241000,
    "config": 227000,
    "aurora-dx-nvidia": 227000,
    "silverblue-asus-nvidia": 225000,
    "akmods-zfs": 225000,
    "sericea-main": 217000,
    "silverblue-surface-nvidia": 203000,
    "bluefin-cli": 198000,
    "silverblue-surface": 177000,
    "bling": 170000,
    "silverblue-asus": 163000,
    "akmods-nvidia-open": 155000,
    "coreos-stable-kernel": 146000,
    "kinoite-asus-nvidia": 143000,
    "akmods-extra": 139000,
    "mate-main": 137000,
    "bazzite-deck-nvidia": 133000,
    "bazzite-arch": 127000,
    "lxqt-main": 124000,
    "bazzite-asus-nvidia": 123000,
    "ubuntu": 119000,
    "sericea-asus-nvidia": 115000,
    "base-asus-nvidia": 113000,
    "kinoite-surface-nvidia": 106000,
    "mate-asus-nvidia": 105000,
    "vauxite-asus-nvidia": 102000,
    "aurora-nvidia": 101000,
    "surface-kernel": 100000,
    "fedora-coreos": 96300,
    "fedora-toolbox": 91500,
    "coreos-testing-kernel": 90900,
    "asus-kernel": 87100,
    "kinoite-asus": 86700,
    "ucore-minimal": 85600,
    "bazzite-kernel": 85300,
    "lxqt-asus-nvidia": 83000,
    "bazzite-asus-nvidia-open": 81500,
    "vauxite-surface-nvidia": 79900,
    "bazzite-asus": 78200,
    "ubuntu-toolbox": 77100,
    "base-surface-nvidia": 76700,
    "sericea-surface-nvidia": 76300,
    "mate-surface-nvidia": 75700,
    "onyx-main": 75300,
    "kinoite-surface": 71900,
    "onyx-nvidia": 68800,
    "ucore-kmods": 68500,
    "boxkit": 67800,
    "mate": 67000,
    "lxqt": 66900,
    "bazzite-ally-gnome": 66600,
    "fsync-kernel": 64300,
    "bluefin-dx-asus-nvidia": 62100,
    "onyx-asus-nvidia": 59000,
    "lxqt-surface-nvidia": 57800,
    "beyond": 57500,
    "lazurite-main": 57300,
    "fedora-distrobox": 53400,
    "bazzite-gnome-asus-nvidia": 52700,
    "bluefin-dx-asus": 52000,
    "bazzite-gnome-asus": 50400,
    "beyond-nvidia": 49200,
    "onyx-surface-nvidia": 46200,
    "bluefin-surface": 44500,
    "bluefin-dx-surface": 44100,
    "bluefin-asus-nvidia": 42900,
    "arch-distrobox": 41600,
    "lxqt-nokmods": 41200,
    "bluefin-asus": 41000,
    "kinoite-nokmods": 40200,
    "silverblue-nokmods": 40000,
    "base-nokmods": 39800,
    "mate-nokmods": 39700,
    "vauxite-nokmods": 35700,
    "deepin-nvidia": 35500,
    "deepin-main": 34100,
    "bluefin-dx-surface-nvidia": 33600,
    "base-asus": 32700,
    "sericea-asus": 32500,
    "bazzite-surface": 32400,
    "vauxite-surface": 32100,
    "ublue-update": 32100,
    "bluefin-surface-nvidia": 31900,
    "bazzite-gnome-surface": 31600,
    "sericea-surface": 31500,
    "base-surface": 30300,
    "lazurite-nvidia": 29800,
    "fedora-coreos-zfs": 29700,
    "vauxite-asus": 29100,
    "aurora-dx-asus-nvidia": 28900,
    "isogenerator": 28400,
    "mate-asus": 27800,
    "bazzite-surface-nvidia": 27400,
    "kera-nvidia": 26700,
    "kera": 26600,
    "mate-surface": 26100,
    "sericea-nokmods": 26100,
    "aurora-surface": 26000,
    "lxqt-surface": 25100,
    "aurora-asus": 24200,
    "lxqt-asus": 24200,
    "fsync-ba-kernel": 23700,
    "bazzite-gnome-asus-nvidia-open": 23400,
    "bazzite-gnome-surface-nvidia": 22700,
    "cosmic-silverblue": 22700,
    "aurora-dx-asus": 22300,
    "obs-studio-portable": 21300,
    "bazzite-arch-gnome": 21100,
    "bazzite-deck-nvidia-gnome": 19600,
    "lazurite-asus-nvidia": 19400,
    "aurora-dx-surface": 19100,
    "endlish-oesque-nvidia": 19000,
    "onyx-asus": 18800,
    "bluefin-hwe": 18300,
    "endlish-oesque": 17900,
    "bluefin-dx-hwe": 17600,
    "onyx-surface": 16900,
    "aurora-asus-nvidia": 16500,
    "aurora-dx-nvidia-open": 16000,
    "aurora-dx-hwe": 14800,
    "arch-distrobox-amdgpupro": 14400,
    "aurora-surface-nvidia": 14300,
    "bluefin-dx-hwe-nvidia": 14100,
    "cosmic-kinoite": 13500,
    "aurora-hwe": 13000,
    "aurora-dx-surface-nvidia": 12900,
    "aurora-dx-hwe-nvidia": 11600,
    "wolfi-toolbox": 11000,
    "lazurite-surface-nvidia": 10900,
    "deepin-asus-nvidia": 10100,
    "aurora-hwe-nvidia": 10000,
    "cosmic": 10000,
    "deepin-surface": 9940,
    "deepin-asus": 9130,
    "deepin-surface-nvidia": 9070,
    "bluefin-dx-nvidia-open": 9040,
    "aurora-nvidia-open": 8080,
    "bluefin-hwe-nvidia": 7800,
    "lazurite-asus": 7200,
    "cosign-generate-keypair": 6770,
    "bluefin-nvidia-open": 6740,
    "ublue-builder": 6540,
    "wolfi-dx-toolbox": 6340,
    "lazurite-surface": 5750,
    "cosmic-nvidia": 4260,
    "bluefin-gdx": 3750,
    "akmods-nvtest": 3230,
    "bazzite-dx": 3030,
    "vauxite": 3000,
    "aurora-dx-hwe-nvidia-open": 2920,
    "bazzite-budgie": 2540,
    "bazzite-budgie-asus": 2310,
    "bazzite-deck-budgie": 2270,
    "bazzite-budgie-surface": 2270,
    "bazzite-ally-budgie": 2240,
    "bazzite-budgie-surface-nvidia": 2160,
    "bazzite-budgie-asus-nvidia": 2150,
    "bazzite-budgie-nvidia": 2140,
    "ccos": 2020,
    "bluefin-dx-hwe-nvidia-open": 1970,
    "bluefin-dx-cli": 1880,
    "wolfi-base": 1850,
    "akmods-nvtest-nvidia": 1830,
    "base-bootc": 1790,
    "bazzite-framegame-budgie": 1740,
    "cosmic-silverblue-nvidia": 1670,
    "bluefin-hwe-nvidia-open": 1670,
    "aurora-hwe-nvidia-open": 1650,
    "docker-distrobox": 1380,
    "bazzite-dx-gnome": 1350,
    "cosmic-kinoite-nvidia": 1300,
    "bling-testing": 1280,
    "extras": 1280,
    "bazzite-dx-nvidia-open": 1280,
    "cosmic-atomic-main": 1200,
    "akmods-nvtest-extra": 916,
    "wolfi-sdk": 903,
    "powershell-toolbox": 893,
    "bazzite-surface-nvidia-open": 772,
    "bazzite-dx-gnome-nvidia-open": 667,
    "bazzite-gnome-surface-nvidia-open": 605,
    "incus-distrobox": 561,
    "sway-atomic-main": 423,
    "bluefin-dx-asus-nvidia-open": 354,
    "aurora-gdx": 318,
    "aurora-dx-asus-nvidia-open": 295,
    "aurora-asus-nvidia-open": 258,
    "aurora-surface-nvidia-open": 256,
    "aurora-dx-surface-nvidia-open": 253,
    "debian-toolbox": 249,
    "budgie-atomic-main": 245,
    "blincusui-distrobox": 243,
    "bazzite-gdx": 241,
    "silverblue-bootc": 238,
    "bluefin-asus-nvidia-open": 212,
    "bluefin-surface-nvidia-open": 209,
    "bluefin-dx-surface-nvidia-open": 208,
    "kinoite-bootc": 202,
    "uupd": 79,
    "push-to-registry-action-ci": 69,
    "kinoite-asahi": 55,
    "sway-atomic-nvidia": 34,
    "dx": 22,
    "budgie-atomic-nvidia": 22,
    "sway-bootc": 17,
    "budgie-bootc": 16,
    "cinnamon-bootc": 16,
    "xfce-bootc": 15,
    "deepin-bootc": 15,
    "lxqt-bootc": 14,
    "mate-bootc": 12,
    "silverblue-asahi": 7,
    "arch-toolbox": 6
  }
}
